{
  "id": "7345678901234567890",
  "title": "泰国香水测评 | 5款平价香水推荐 🌸",
  "description": "今天测评5款泰国超火的平价香水！每款都超好闻 💕 #น้ำหอม #รีวิวน้ำหอม #perfumethailand #香水推荐",
  "uploader": "PerfumeQueenTH",
  "uploader_id": "perfumequeenth",
  "upload_date": "20260305",
  "duration": 58,
  "view_count": 285000,
  "like_count": 18500,
  "comment_count": 890,
  "repost_count": 1200,
  "tags": ["น้ำหอม", "รีวิวน้ำหอม", "perfumethailand", "香水推荐", "平价香水"],
  "webpage_url": "https://www.tiktok.com/@perfumequeenth/video/7345678901234567890"
}
